nstuff.py
nstuff-0.2.1.dist-info/LICENSE
nstuff-0.2.1.dist-info/METADATA
nstuff-0.2.1.dist-info/WHEEL
nstuff-0.2.1.dist-info/top_level.txt
nstuff-0.2.1.dist-info/RECORD
