Metadata-Version: 2.1
Name: nstuff
Version: 0.2.1
Summary: nstuff is a replacement for cgi.MiniFieldStorage, nstuff parses CGI POST and GET data into a dict.
Home-page: https://github.com/superkabuki/nstuff
Author: Adrian of Doom
Author-email: spam@iodisco.com
Classifier: License :: OSI Approved :: Sleepycat License
Classifier: Environment :: Console
Classifier: Operating System :: OS Independent
Classifier: Programming Language :: Python :: 3.8
Classifier: Programming Language :: Python :: Implementation :: PyPy
Classifier: Programming Language :: Python :: Implementation :: CPython
Requires-Python: >=3.8
License-File: LICENSE
